msgapp/__init__.py
msgapp/_app.py
msgapp/_executor.py
msgapp/_parser.py
msgapp/_producer.py
msgapp/parsers/__init__.py
msgapp/parsers/json.py
msgapp/producers/__init__.py
msgapp/producers/memory.py
msgapp/producers/pubsub.py
msgapp/py.typed
msgapp-0.1.5.dist-info/LICENSE.txt
msgapp-0.1.5.dist-info/WHEEL
msgapp-0.1.5.dist-info/METADATA
msgapp-0.1.5.dist-info/RECORD
