Metadata-Version: 2.1
Name: msgapp
Version: 0.1.5
Summary: Declarative message processing applications
Home-page: https://github.com/adriangb/msgapp
License: MIT
Author: Adrian Garcia Badaracco
Author-email: dev@adriangb.com
Requires-Python: >=3.7,<4
Classifier: License :: OSI Approved :: MIT License
Classifier: Programming Language :: Python :: 3
Classifier: Programming Language :: Python :: 3.7
Classifier: Programming Language :: Python :: 3.8
Classifier: Programming Language :: Python :: 3.9
Classifier: Programming Language :: Python :: 3.10
Classifier: Programming Language :: Python :: 3.11
Provides-Extra: dev
Provides-Extra: json
Provides-Extra: pubsub
Requires-Dist: anyio (>=3.6.1)
Requires-Dist: google-cloud-pubsub (>=2.13.4); extra == "pubsub" or extra == "dev"
Requires-Dist: pydantic (>=1.9.1); extra == "json" or extra == "dev"
Requires-Dist: typing-extensions (>=4.3.0,<5.0.0); python_version < "3.9"
